sunnyside/__init__.py
sunnyside/currentWeather.py
sunnyside/fiveDayForecast.py
sunnyside/onecall.py
sunnyside/sunnyside.py
sunnyside-2.0.0.dist-info/LICENSE
sunnyside-2.0.0.dist-info/METADATA
sunnyside-2.0.0.dist-info/WHEEL
sunnyside-2.0.0.dist-info/top_level.txt
sunnyside-2.0.0.dist-info/RECORD
