Metadata-Version: 2.1
Name: sunnyside
Version: 2.0.0
Summary: Mini python wrapper for OpenWeather API's one call, current and forecast5 services.
Home-page: https://github.com/junqili259/Sunnyside/
Author: Jun Qi Li
Author-email: JunQi.Li63@myhunter.cuny.com
License: UNKNOWN
Platform: UNKNOWN
Classifier: Programming Language :: Python :: 3.6
Classifier: Programming Language :: Python :: 3.7
Classifier: Programming Language :: Python :: 3.8
Classifier: License :: OSI Approved :: MIT License
Classifier: Operating System :: OS Independent
Requires-Python: >=3.6
